swxg/__init__.py
swxg/fit.py
swxg/make_figures.py
swxg/model.py
swxg/synthesize.py
swxg/test_wx/__init__.py
swxg/test_wx/example_daily.pkl
swxg/test_wx/example_monthly.pkl
swxg-0.4.0.dist-info/licenses/LICENSE
swxg-0.4.0.dist-info/METADATA
swxg-0.4.0.dist-info/WHEEL
swxg-0.4.0.dist-info/top_level.txt
swxg-0.4.0.dist-info/RECORD
