Metadata-Version: 2.4
Name: swxg
Version: 0.4.0
Summary: Fast, region-agnostic stochastic weather generation
Author-email: Alexander Thames <alexander.b.thames@gmail.com>
License-Expression: MIT
Project-URL: Homepage, https://github.com/xthames/swxg
Project-URL: Documentation, https://swxg.readthedocs.io/
Project-URL: Repository, https://github.com/xthames/swxg.git
Keywords: swxg,stochastic,synthetic,weather,generator,semiparametric,copula,precipitation,temperature
Classifier: Development Status :: 3 - Alpha
Classifier: Intended Audience :: Science/Research
Classifier: Topic :: Scientific/Engineering :: Atmospheric Science
Classifier: Topic :: Scientific/Engineering :: Hydrology
Classifier: Programming Language :: Python :: 3.11
Requires-Python: >=3.10
License-File: LICENSE
Requires-Dist: copulae>=0.8
Requires-Dist: copulas<0.12,>=0.10
Requires-Dist: hmmlearn>=0.3
Requires-Dist: matplotlib>=3.8
Requires-Dist: numpy==2.0
Requires-Dist: pandas>=2.1
Requires-Dist: scikit-learn>=1.4
Requires-Dist: scipy>=1.15
Requires-Dist: statsmodels<0.15,>=0.14
Dynamic: license-file
